{"language": "ENG", "publishing_work_items.type": "3", "country_of_publication": "USA", "idno": "0514-7913 SC 80001708 4556453 0514-7913", "publication_type": "10", "subject": "", "publishing_work_items.value": "v.", "publisher.publisher_name": "REGIONAL PLAN ASSOCIATION.", "contributor.name": "REGIONAL PLAN ASSOCIATION (NEW YORK)", "contributor.role": "2", "title": "Zoning bulletin Zoning bulletin", "idno.type": "VALISSN VALLCCN OCLCNUM VALISSNL", "publisher.place_of_publication": "NEW YORK,", "publishing_work_items.unit": "7"}